swvo/__init__.py
swvo/io/__init__.py
swvo/io/decorators.py
swvo/io/exceptions.py
swvo/io/utils.py
swvo/io/RBMDataSet/RBMDataSet.py
swvo/io/RBMDataSet/RBMDataSetElPaso.py
swvo/io/RBMDataSet/RBMDataSetManager.py
swvo/io/RBMDataSet/RBMNcDataSet.py
swvo/io/RBMDataSet/__init__.py
swvo/io/RBMDataSet/bin_and_interpolate_to_model_grid.py
swvo/io/RBMDataSet/custom_enums.py
swvo/io/RBMDataSet/interp_functions.py
swvo/io/RBMDataSet/utils.py
swvo/io/RBMDataSet/scripts/__init__.py
swvo/io/RBMDataSet/scripts/create_RBSP_line_data.py
swvo/io/dst/__init__.py
swvo/io/dst/omni.py
swvo/io/dst/read_dst_from_multiple_models.py
swvo/io/dst/wdc.py
swvo/io/f10_7/__init__.py
swvo/io/f10_7/omni.py
swvo/io/f10_7/read_f107_from_multiple_models.py
swvo/io/f10_7/swpc.py
swvo/io/hp/__init__.py
swvo/io/hp/ensemble.py
swvo/io/hp/gfz.py
swvo/io/hp/read_hp_from_multiple_models.py
swvo/io/kp/__init__.py
swvo/io/kp/ensemble.py
swvo/io/kp/niemegk.py
swvo/io/kp/omni.py
swvo/io/kp/read_kp_from_multiple_models.py
swvo/io/kp/swpc.py
swvo/io/omni/__init__.py
swvo/io/omni/omni_high_res.py
swvo/io/omni/omni_low_res.py
swvo/io/plasmasphere/__init__.py
swvo/io/plasmasphere/read_plasmasphere.py
swvo/io/plasmasphere/read_plasmasphere_combined_inputs.py
swvo/io/solar_wind/__init__.py
swvo/io/solar_wind/ace.py
swvo/io/solar_wind/dscovr.py
swvo/io/solar_wind/omni.py
swvo/io/solar_wind/read_solar_wind_from_multiple_models.py
swvo/io/solar_wind/swift.py
swvo-1.1.0.dist-info/licenses/LICENSES/Apache-2.0.txt
swvo-1.1.0.dist-info/METADATA
swvo-1.1.0.dist-info/WHEEL
swvo-1.1.0.dist-info/top_level.txt
swvo-1.1.0.dist-info/RECORD
