Metadata-Version: 2.4
Name: swvo
Version: 1.1.0
Summary: Tools for downloading and reading space-weather data and geomagnetic indices.
Author-email: "Bernhard Haas, Sahil Jhawar, Stefano Bianco, Ruggero Vasile" <sec15@gfz.de>
License-Expression: Apache-2.0
Project-URL: Homepage, https://github.com/GFZ/SWVO
Project-URL: Documentation, https://swvo.readthedocs.io/en/latest/
Project-URL: Download, https://pypi.org/project/swvo/#files
Project-URL: Tracker, https://github.com/GFZ/SWVO/issues
Classifier: Programming Language :: Python :: 3
Classifier: Programming Language :: Python :: 3.11
Classifier: Programming Language :: Python :: 3.12
Classifier: Programming Language :: Python :: 3.13
Classifier: Operating System :: POSIX
Classifier: Operating System :: Unix
Classifier: Operating System :: MacOS
Requires-Python: >=3.11
License-File: LICENSES/Apache-2.0.txt
Requires-Dist: numpy
Requires-Dist: pandas
Requires-Dist: wget
Requires-Dist: mat73
Requires-Dist: scipy
Requires-Dist: pytest
Requires-Dist: matplotlib
Requires-Dist: requests
Requires-Dist: wget
Requires-Dist: distance
Requires-Dist: tqdm
Requires-Dist: pytest-mock
Requires-Dist: netcdf4
Provides-Extra: docs
Requires-Dist: sphinx-copybutton; extra == "docs"
Requires-Dist: sphinx-github-changelog; extra == "docs"
Requires-Dist: sphinx; extra == "docs"
Requires-Dist: pydata-sphinx-theme; extra == "docs"
Requires-Dist: myst-parser; extra == "docs"
Requires-Dist: alabaster; extra == "docs"
Requires-Dist: docutils; extra == "docs"
Requires-Dist: imagesize; extra == "docs"
Requires-Dist: numpydoc; extra == "docs"
Requires-Dist: linkify-it-py; extra == "docs"
Dynamic: license-file
